aceCommon/__init__.py
aceCommon/classCommon.py
aceCommon/fileCommon.py
aceCommon/listWorkCommon.py
aceCommon/mathCommon.py
aceCommon/osCommon.py
aceCommon/stringCommon.py
aceCommon/timeCommon.py
lukhed_basic_utils/__init__.py
lukhed_basic_utils/chartJsCommon.py
lukhed_basic_utils/classCommon.py
lukhed_basic_utils/commonCommon.py
lukhed_basic_utils/fileCommon.py
lukhed_basic_utils/githubCommon.py
lukhed_basic_utils/imageCommon.py
lukhed_basic_utils/listWorkCommon.py
lukhed_basic_utils/mathCommon.py
lukhed_basic_utils/matplotlibBarCharts.py
lukhed_basic_utils/matplotlibBasics.py
lukhed_basic_utils/matplotlibFormatting.py
lukhed_basic_utils/matplotlibLineCharts.py
lukhed_basic_utils/matplotlibPieCharts.py
lukhed_basic_utils/matplotlibScatter.py
lukhed_basic_utils/matplotlibSpecial.py
lukhed_basic_utils/osCommon.py
lukhed_basic_utils/requestsCommon.py
lukhed_basic_utils/sqlCommon.py
lukhed_basic_utils/stringCommon.py
lukhed_basic_utils/timeCommon.py
lukhed_basic_utils-1.6.10.dist-info/LICENSE
lukhed_basic_utils-1.6.10.dist-info/METADATA
lukhed_basic_utils-1.6.10.dist-info/WHEEL
lukhed_basic_utils-1.6.10.dist-info/top_level.txt
lukhed_basic_utils-1.6.10.dist-info/RECORD
