Metadata-Version: 2.1
Name: lukhed-basic-utils
Version: 1.6.10
Summary: A collection of basic utility functions
Home-page: https://github.com/lukhed/lukhed_basic_utils
Author: lukhed
Author-email: lukhed.mail@gmail.com
Classifier: Programming Language :: Python :: 3
Classifier: License :: OSI Approved :: MIT License
Classifier: Operating System :: OS Independent
Requires-Python: >=3.9
License-File: LICENSE
Requires-Dist: python-dateutil>=2.9.0
Requires-Dist: requests>=2.32.3
Requires-Dist: beautifulsoup4>=4.12.3
Requires-Dist: fake-useragent>=2.0.3
Requires-Dist: tzdata>=2023.3
Requires-Dist: PyGithub>=2.5.0
Requires-Dist: matplotlib>=3.10.1
Requires-Dist: numpy>=2.2.4
Requires-Dist: pandas>=2.2.3
Requires-Dist: scipy>=1.15.2
Requires-Dist: mysql-connector-python>=8.0.0
Requires-Dist: psycopg2-binary>=2.9.10
